shuttleasgi/__init__.py
shuttleasgi/asgi.pyi
shuttleasgi/baseapp.c
shuttleasgi/baseapp.cp313-win_amd64.pyd
shuttleasgi/baseapp.pxd
shuttleasgi/baseapp.py
shuttleasgi/baseapp.pyi
shuttleasgi/baseapp.pyx
shuttleasgi/contents.c
shuttleasgi/contents.cp313-win_amd64.pyd
shuttleasgi/contents.pxd
shuttleasgi/contents.py
shuttleasgi/contents.pyi
shuttleasgi/contents.pyx
shuttleasgi/context.py
shuttleasgi/cookies.c
shuttleasgi/cookies.cp313-win_amd64.pyd
shuttleasgi/cookies.pxd
shuttleasgi/cookies.py
shuttleasgi/cookies.pyi
shuttleasgi/cookies.pyx
shuttleasgi/exceptions.c
shuttleasgi/exceptions.cp313-win_amd64.pyd
shuttleasgi/exceptions.pxd
shuttleasgi/exceptions.py
shuttleasgi/exceptions.pyi
shuttleasgi/exceptions.pyx
shuttleasgi/headers.c
shuttleasgi/headers.cp313-win_amd64.pyd
shuttleasgi/headers.pxd
shuttleasgi/headers.py
shuttleasgi/headers.pyi
shuttleasgi/headers.pyx
shuttleasgi/messages.c
shuttleasgi/messages.cp313-win_amd64.pyd
shuttleasgi/messages.pxd
shuttleasgi/messages.py
shuttleasgi/messages.pyi
shuttleasgi/messages.pyx
shuttleasgi/multipart.py
shuttleasgi/normalization.py
shuttleasgi/py.typed
shuttleasgi/ranges.py
shuttleasgi/scribe.c
shuttleasgi/scribe.cp313-win_amd64.pyd
shuttleasgi/scribe.pxd
shuttleasgi/scribe.py
shuttleasgi/scribe.pyi
shuttleasgi/scribe.pyx
shuttleasgi/url.c
shuttleasgi/url.cp313-win_amd64.pyd
shuttleasgi/url.pxd
shuttleasgi/url.py
shuttleasgi/url.pyi
shuttleasgi/url.pyx
shuttleasgi/client/__init__.py
shuttleasgi/client/connection.py
shuttleasgi/client/cookies.py
shuttleasgi/client/exceptions.py
shuttleasgi/client/parser.py
shuttleasgi/client/pool.py
shuttleasgi/client/session.py
shuttleasgi/common/__init__.py
shuttleasgi/common/types.py
shuttleasgi/common/files/__init__.py
shuttleasgi/common/files/asyncfs.py
shuttleasgi/common/files/info.py
shuttleasgi/common/files/pathsutils.py
shuttleasgi/middlewares/__init__.py
shuttleasgi/middlewares/shuttle_headers.c
shuttleasgi/middlewares/shuttle_headers.cp313-win_amd64.pyd
shuttleasgi-5.7.3.dist-info/licenses/LICENSE
shuttleasgi-5.7.3.dist-info/METADATA
shuttleasgi-5.7.3.dist-info/WHEEL
shuttleasgi-5.7.3.dist-info/top_level.txt
shuttleasgi-5.7.3.dist-info/RECORD
