Metadata-Version: 2.4
Name: shuttleasgi
Version: 5.7.3
Summary: Fork of BlackSheep, the ex fastest web framework for Python asyncio
Author-email: Roberto Prevato <roberto.prevato@gmail.com>
Maintainer-email: Christian Heru Mes <chris@shuttleai.app>
License: MIT License
Project-URL: Website, https://shuttleai.app
Project-URL: Homepage, https://github.com/shuttleai/ShuttleASGI
Project-URL: Bug Tracker, https://github.com/shuttleai/shuttleasgi/issues
Keywords: shuttleasgi,web framework,asyncio,blacksheep,shuttleai
Classifier: Development Status :: 5 - Production/Stable
Classifier: Programming Language :: Python :: 3.9
Classifier: Programming Language :: Python :: 3.10
Classifier: Programming Language :: Python :: 3.11
Classifier: Programming Language :: Python :: 3.12
Classifier: Programming Language :: Python :: 3.13
Classifier: Environment :: Web Environment
Classifier: Operating System :: OS Independent
Classifier: Framework :: AsyncIO
Requires-Python: >=3.8
License-File: LICENSE
Requires-Dist: certifi>=2025.4.26
Requires-Dist: guardpost>=1.0.2
Requires-Dist: rodi~=2.0.8
Requires-Dist: essentials<2.0,>=1.1.4
Requires-Dist: essentials-openapi<2.0,>=1.2.0
Requires-Dist: python-dateutil~=2.9.0
Requires-Dist: itsdangerous~=2.2.0
Requires-Dist: uuid-utils~=0.11.0
Provides-Extra: jinja
Requires-Dist: Jinja2~=3.1.6; extra == "jinja"
Provides-Extra: full
Requires-Dist: cryptography<46.0.0,>=45.0.2; extra == "full"
Requires-Dist: PyJWT~=2.10.1; extra == "full"
Requires-Dist: websockets~=15.0.1; extra == "full"
Requires-Dist: Jinja2~=3.1.6; extra == "full"
Provides-Extra: cython
Requires-Dist: httptools>=0.6.4; extra == "cython"
Provides-Extra: purepython
Requires-Dist: h11==0.16.0; extra == "purepython"
Dynamic: license-file
